tardis_spac/__init__.py
tardis_spac/external/__init__.py
tardis_spac/external/cellcharter_cluster.py
tardis_spac/external/cluster_specific.py
tardis_spac/stats/__init__.py
tardis_spac/stats/_global.py
tardis_spac/stats/_local.py
tardis_spac/utils/__init__.py
tardis_spac/utils/io.py
tardis_spac/utils/plot.py
tardis_spac/utils/preprocess.py
tardis_spac-0.7.1.dist-info/LICENSE
tardis_spac-0.7.1.dist-info/METADATA
tardis_spac-0.7.1.dist-info/WHEEL
tardis_spac-0.7.1.dist-info/top_level.txt
tardis_spac-0.7.1.dist-info/RECORD
