Metadata-Version: 2.1
Name: tardis_spac
Version: 0.7.1
Summary: TArget pRioritization toolkit for perturbation Data In Spatial-omics
Author: pkuTrasond
Author-email: barry_2001@stu.pku.edu.cn
Classifier: Programming Language :: Python :: 3
Classifier: License :: OSI Approved :: MIT License
Classifier: Operating System :: OS Independent
Requires-Python: >=3.8
License-File: LICENSE
Requires-Dist: numpy
Requires-Dist: pandas
Requires-Dist: scipy
Requires-Dist: scikit-learn
Requires-Dist: scikit-bio
Requires-Dist: matplotlib
Requires-Dist: seaborn
Requires-Dist: scanpy
Requires-Dist: statsmodels
Requires-Dist: tqdm
